__init__.py
zella/__init__.py
zella/_client.py
zella/config.py
zella/version.py
zella/resources/__init__.py
zella/resources/callbacks/__init__.py
zella/resources/callbacks/langchain_callback.py
zella/resources/chat/__init__.py
zella/resources/chat/chat.py
zella/resources/chat/completions.py
zella/resources/completions/__init__.py
zella/resources/completions/completions.py
zella/resources/embedding/__init__.py
zella/resources/embedding/embedding.py
zella/resources/logger/__init__.py
zella/resources/logger/log_consumer.py
zella/resources/logger/logger.py
zella/resources/prompt/__init__.py
zella/resources/prompt/prompt.py
zella-0.0.5.dist-info/LICENSE.md
zella-0.0.5.dist-info/METADATA
zella-0.0.5.dist-info/WHEEL
zella-0.0.5.dist-info/top_level.txt
zella-0.0.5.dist-info/RECORD
