Metadata-Version: 2.1
Name: zella
Version: 0.0.5
Summary: Python SDK for accessing Zella AI for building AI apps
Author-email: Team Zella <dev@zella.ai>
Project-URL: Homepage, https://github.com/ZellaAI/zella-py
Project-URL: Issues, https://github.com/ZellaAI/zella-py/issues
Classifier: Programming Language :: Python :: 3
Classifier: License :: OSI Approved :: MIT License
Classifier: Operating System :: OS Independent
Requires-Python: >=3.8
License-File: LICENSE.md
Requires-Dist: httpx >=0.25
